__init__.py
energia/__init__.py
energia/export.py
energia/_core/__init__.py
energia/_core/_component.py
energia/_core/_dimension.py
energia/_core/_hash.py
energia/_core/_name.py
energia/_core/_x.py
energia/components/__init__.py
energia/components/commodities/__init__.py
energia/components/commodities/commodity.py
energia/components/commodities/currency.py
energia/components/commodities/emission.py
energia/components/commodities/land.py
energia/components/commodities/material.py
energia/components/commodities/misc.py
energia/components/commodities/resource.py
energia/components/game/__init__.py
energia/components/game/couple.py
energia/components/game/player.py
energia/components/graph/__init__.py
energia/components/graph/edge.py
energia/components/graph/node.py
energia/components/impact/__init__.py
energia/components/impact/categories.py
energia/components/impact/indicator.py
energia/components/measure/__init__.py
energia/components/measure/unit.py
energia/components/operations/__init__.py
energia/components/operations/free.py
energia/components/operations/operation.py
energia/components/operations/process.py
energia/components/operations/storage.py
energia/components/operations/trade.py
energia/components/operations/transport.py
energia/components/spatial/__init__.py
energia/components/spatial/linkage.py
energia/components/spatial/location.py
energia/components/temporal/__init__.py
energia/components/temporal/_calendar.py
energia/components/temporal/lag.py
energia/components/temporal/modes.py
energia/components/temporal/periods.py
energia/components/temporal/scales.py
energia/dimensions/__init__.py
energia/dimensions/game.py
energia/dimensions/impact.py
energia/dimensions/problem.py
energia/dimensions/space.py
energia/dimensions/system.py
energia/dimensions/time.py
energia/library/__init__.py
energia/library/aliases.py
energia/library/components.py
energia/library/external.py
energia/library/instructions.py
energia/library/recipes.py
energiapy-2.1.6.dist-info/licenses/LICENSE
energiapy-2.1.6.dist-info/METADATA
energiapy-2.1.6.dist-info/WHEEL
energiapy-2.1.6.dist-info/top_level.txt
energiapy-2.1.6.dist-info/RECORD
