Metadata-Version: 2.4
Name: energiapy
Version: 2.1.6
Summary: For multiscale modeling and optimization of energy systems
Author-email: Rahul Kakodkar <cacodcar@gmail.com>, "Efstratios N. Pistikopoulos" <stratos@tamu.edu>
Maintainer-email: Rahul Kakodkar <cacodcar@gmail.com>
License: MIT License
Project-URL: Homepage, https://github.com/TAMUparametric/energiapy
Project-URL: Issues, https://github.com/TAMUparametric/energiapy/issues
Project-URL: Changelog, https://github.com/yourusername/yourrepo/blob/main/CHANGELOG.md
Keywords: modeling,optimization,energy systems,ems,multiscale
Classifier: Programming Language :: Python :: 3.13
Classifier: Programming Language :: Python :: 3.12
Classifier: License :: OSI Approved :: MIT License
Classifier: Operating System :: OS Independent
Requires-Python: >=3.12
License-File: LICENSE
Requires-Dist: gana
Requires-Dist: ppopt
Requires-Dist: IPython
Requires-Dist: matplotlib
Requires-Dist: scipy
Requires-Dist: pandas
Requires-Dist: numpy
Requires-Dist: gurobipy
Provides-Extra: all
Requires-Dist: pvlib; extra == "all"
Requires-Dist: windpowerlib; extra == "all"
Requires-Dist: h5pyd; extra == "all"
Provides-Extra: test
Requires-Dist: coverage; extra == "test"
Requires-Dist: pytest; extra == "test"
Requires-Dist: pytest-cov; extra == "test"
Requires-Dist: hypothesis; extra == "test"
Requires-Dist: flake8; extra == "test"
Provides-Extra: docs
Requires-Dist: sphinx; extra == "docs"
Requires-Dist: sphinx-book-theme; extra == "docs"
Requires-Dist: nbsphinx; extra == "docs"
Requires-Dist: sphinx_mdinclude; extra == "docs"
Requires-Dist: myst-nb; extra == "docs"
Requires-Dist: sphinxcontrib-bibtex; extra == "docs"
Requires-Dist: sphinx-copybutton; extra == "docs"
Requires-Dist: sphinx-togglebutton; extra == "docs"
Requires-Dist: sphinx-thebe; extra == "docs"
Requires-Dist: sphinx-design; extra == "docs"
Requires-Dist: sphinx-examples; extra == "docs"
Requires-Dist: sphinx-tabs; extra == "docs"
Requires-Dist: sphinxext-opengraph; extra == "docs"
Dynamic: license-file
